noctsleepy/__init__.py
noctsleepy/__main__.py
noctsleepy/cli.py
noctsleepy/main.py
noctsleepy/timezones.py
noctsleepy/io/__init__.py
noctsleepy/io/readers.py
noctsleepy/processing/__init__.py
noctsleepy/processing/sleep_variables.py
noctsleepy/processing/utils.py
noctsleepy-0.1.0.dist-info/METADATA
noctsleepy-0.1.0.dist-info/WHEEL
noctsleepy-0.1.0.dist-info/entry_points.txt
noctsleepy-0.1.0.dist-info/licenses/LICENSE
noctsleepy-0.1.0.dist-info/RECORD
