Metadata-Version: 2.4
Name: noctsleepy
Version: 0.1.0
Summary: This package provides a toolbox of functions to compute key metrics about nocturnal sleep from already processed wrist-worn actigraphy data.
Author-email: Adam Santorelli <adam.santorelli@childmind.org>, Reinder Vos de Wael <reinder.vosdewael@childmind.org>
License-Expression: LGPL-2.1-only
License-File: LICENSE
Requires-Python: >=3.11
Requires-Dist: numpy>=2.3.5
Requires-Dist: polars>=1.31.0
Requires-Dist: typer>=0.20.0
Requires-Dist: tzdata>=2025.2
